kubernetes/__init__.py
kubernetes/client.py
kubernetes/parser.py
kubernetes/test_client.py
kubernetes/test_parser.py
telegraf_kubernetes-0.1.6.data/scripts/telegraf-kubernetes
telegraf_kubernetes-0.1.6.dist-info/LICENSE
telegraf_kubernetes-0.1.6.dist-info/METADATA
telegraf_kubernetes-0.1.6.dist-info/WHEEL
telegraf_kubernetes-0.1.6.dist-info/top_level.txt
telegraf_kubernetes-0.1.6.dist-info/RECORD
