Metadata-Version: 2.1
Name: telegraf-kubernetes
Version: 0.1.6
Summary: Plugin for Telegraf for gathering statistics from Kubernetes
Home-page: https://github.com/pmastalerz/telegraf-kubernetes
Author: Pawel Mastalerz
Author-email: pawel@mastalerz.info
License: MIT
Platform: UNKNOWN
Classifier: Development Status :: 4 - Beta
Classifier: Intended Audience :: System Administrators
Classifier: License :: OSI Approved :: MIT License
Classifier: Programming Language :: Python :: 2
Classifier: Operating System :: OS Independent
Requires-Dist: requests (>=2.19)
Requires-Dist: influx-line-protocol (>=0.1.2)
Requires-Dist: mock; python_version < "3.3"
